supervisor_event_listeners/__init__.py
supervisor_event_listeners/eventexec.py
supervisor_event_listeners/fseventwatcher.py
supervisor_event_listeners/processrestarter.py
supervisor_event_listeners-0.0.1.dist-info/DESCRIPTION.rst
supervisor_event_listeners-0.0.1.dist-info/METADATA
supervisor_event_listeners-0.0.1.dist-info/RECORD
supervisor_event_listeners-0.0.1.dist-info/WHEEL
supervisor_event_listeners-0.0.1.dist-info/entry_points.txt
supervisor_event_listeners-0.0.1.dist-info/metadata.json
supervisor_event_listeners-0.0.1.dist-info/top_level.txt
