Metadata-Version: 2.0
Name: supervisor-event-listeners
Version: 0.0.1
Summary: UNKNOWN
Home-page: UNKNOWN
Author: UNKNOWN
Author-email: UNKNOWN
License: UNKNOWN
Platform: UNKNOWN
Requires-Dist: supervisor
Requires-Dist: watchdog
